bolcan/__init__.py
bolcan/pipeline_eng.py
bolcan-0.0.7.dist-info/LICENSE
bolcan-0.0.7.dist-info/METADATA
bolcan-0.0.7.dist-info/WHEEL
bolcan-0.0.7.dist-info/top_level.txt
bolcan-0.0.7.dist-info/RECORD
