Metadata-Version: 2.1
Name: bolcan
Version: 0.0.7
Summary: A Python package offering essential tools for petroleum and other engineering calculations
Home-page: https://github.com/Jnyame21/bolcan
Author: Justice Nyame
Author-email: nyamejustice2000@gmail.com
Classifier: Programming Language :: Python :: 3
Classifier: License :: OSI Approved :: MIT License
Classifier: Operating System :: OS Independent
Requires-Python: >=3.6
License-File: LICENSE
Requires-Dist: pandas
